{ "_id" : 41, "name" : " " }
{ "_id" : 45, "name" : " a" }
{ "_id" : 26, "name" : "4" }
{ "_id" : 27, "name" : "5" }
{ "_id" : 28, "name" : "6" }
{ "_id" : 29, "name" : "7a" }
{ "_id" : 24, "name" : "a" }
{ "_id" : 38, "name" : "aaa" }
{ "_id" : 37, "name" : "aaaa" }
{ "_id" : 34, "name" : "asa" }
{ "_id" : 43, "name" : "asasdf" }
{ "_id" : 30, "name" : "asdf" }
{ "_id" : 42, "name" : "asoiehfuawef" }
{ "_id" : 25, "name" : "b" }
{ "_id" : 36, "name" : "nnnn" }
{ "_id" : 33, "name" : "q" }
{ "_id" : 32, "name" : "qwe" }
{ "_id" : 31, "name" : "qwer" }
{ "_id" : 39, "name" : "sa" }
{ "_id" : 46, "name" : "safwaefd" }
{ "_id" : 40, "name" : "ss" }
{ "_id" : 1, "name" : "toitoi" }
{ "_id" : 44, "name" : "wew" }
{ "_id" : 35, "name" : "ㅁ" }
{ "_id" : 2, "name" : "깃토이" }
{ "_id" : 4, "name" : "뷰티토이" }
{ "_id" : 6, "name" : "산타" }
{ "_id" : 7, "name" : "산타할아버지는 알고 계신대 누가 착한앤지" }
{ "_id" : 5, "name" : "소토이" }
{ "_id" : 13, "name" : "일이삼사오육칠팔구십일이삼사오육칠팔구십일이삼사오" }
{ "_id" : 3, "name" : "플토이" }